anvil_app_server/Blank.zip
anvil_app_server/Default.zip
anvil_app_server/TodoList.zip
anvil_app_server/__init__.py
anvil_app_server/shell.py
anvil_downlink_host/__init__.py
anvil_downlink_host/memory.py
anvil_downlink_host/pdf_renderer.py
anvil_downlink_host/run.py
anvil_downlink_host/full_python/__init__.py
anvil_downlink_host/full_python/worker.py
anvil_downlink_host/full_python/worker_cache.py
anvil_downlink_util/__init__.py
anvil_downlink_util/pipes.py
anvil_downlink_util/tracing/__init__.py
anvil_downlink_util/tracing/dummy.py
anvil_downlink_util/tracing/impl.py
anvil_downlink_worker/__init__.py
anvil_downlink_worker/exec2.py
anvil_downlink_worker/exec3.py
anvil_downlink_worker/full_python_worker.py
anvil_downlink_worker/anvil/__init__.py
anvil_downlink_worker/anvil/_components.py
anvil_downlink_worker/anvil/_form_templating.py
anvil_downlink_worker/anvil/_serialise.py
anvil_downlink_worker/anvil/_server.py
anvil_downlink_worker/anvil/_threaded_server.py
anvil_downlink_worker/anvil/designer.py
anvil_downlink_worker/anvil/email.py
anvil_downlink_worker/anvil/history.py
anvil_downlink_worker/anvil/http.py
anvil_downlink_worker/anvil/js.py
anvil_downlink_worker/anvil/media.py
anvil_downlink_worker/anvil/mpl_util.py
anvil_downlink_worker/anvil/pdf.py
anvil_downlink_worker/anvil/regex.py
anvil_downlink_worker/anvil/secrets.py
anvil_downlink_worker/anvil/server.py
anvil_downlink_worker/anvil/stripe.py
anvil_downlink_worker/anvil/tz.py
anvil_downlink_worker/anvil/util.py
anvil_downlink_worker/anvil/ext_data/__init__.py
anvil_downlink_worker/anvil/ext_data/impl/__init__.py
anvil_downlink_worker/anvil/ext_data/impl/lazy_iter.py
anvil_downlink_worker/anvil/ext_data/impl/backends/__init__.py
anvil_downlink_worker/anvil/ext_data/impl/backends/sql.py
anvil_downlink_worker/anvil/facebook/__init__.py
anvil_downlink_worker/anvil/facebook/auth.py
anvil_downlink_worker/anvil/files/__init__.py
anvil_downlink_worker/anvil/google/__init__.py
anvil_app_server-1.15.0.dist-info/METADATA
anvil_app_server-1.15.0.dist-info/WHEEL
anvil_app_server-1.15.0.dist-info/entry_points.txt
anvil_app_server-1.15.0.dist-info/top_level.txt
anvil_app_server-1.15.0.dist-info/RECORD
