Metadata-Version: 2.4
Name: anvil-app-server
Version: 1.15.0
Summary: A standalone server for Anvil full-stack Python web apps
Home-page: https://anvil.works
Author: Anvil
Author-email: contact@anvil.works
License: GNU Affero General Public License v3
Project-URL: Source Code, https://github.com/anvil-works/anvil-runtime
Keywords: anvil web apps standalone browser Python
Classifier: License :: OSI Approved :: GNU Affero General Public License v3
Requires-Dist: pychrome==0.2.4
Requires-Dist: anvil-uplink>=0.6.0
Requires-Dist: progressbar2
Requires-Dist: wheel
Requires-Dist: psutil
Dynamic: author
Dynamic: author-email
Dynamic: classifier
Dynamic: description
Dynamic: description-content-type
Dynamic: home-page
Dynamic: keywords
Dynamic: license
Dynamic: project-url
Dynamic: requires-dist
Dynamic: summary
